spare_scores/__init__.py
spare_scores/classes.py
spare_scores/cli.py
spare_scores/data_prep.py
spare_scores/mlp.py
spare_scores/mlp_torch.py
spare_scores/spare.py
spare_scores/svm.py
spare_scores/util.py
spare_scores/data/example_data.csv
spare_scores/data/example_data_ROIs.csv
spare_scores/data/example_data_demographics.csv
spare_scores/mdl/SVM_ISTAGING_AD_CN.pkl.gz
spare_scores/mdl/mdl_SPARE_AD_hMUSE_single.pkl.gz
spare_scores/mdl/mdl_SPARE_BA_hMUSE_single.pkl.gz
spare_scores/mdl/mdl_diSPARE_AD_hMUSE_single.pkl.gz
spare_scores/mdl/mdl_diSPARE_BA_hMUSE_single.pkl.gz
spare_scores/mdl/nnUnet_SVM_Regressor_folder1.pkl.gz
spare_scores/mdl/unnorm_AD_MLPTorch_Classifier_folder1.pkl.gz
spare_scores/mdl/unnorm_age_MLPTorch_Regressor_folder1.pkl.gz
spare_scores-1.2.6.dist-info/LICENSE
spare_scores-1.2.6.dist-info/METADATA
spare_scores-1.2.6.dist-info/WHEEL
spare_scores-1.2.6.dist-info/entry_points.txt
spare_scores-1.2.6.dist-info/top_level.txt
spare_scores-1.2.6.dist-info/RECORD
