Metadata-Version: 2.2
Name: spare_scores
Version: 1.2.6
Summary: Compute characteristic brain signatures of your case population.
Author: Gyujoon Hwang, George Aidinis
Author-email: ghwang1106@gmail.com, aidinisg@pennmedicine.upenn.edu
License: https://www.med.upenn.edu/cbica/software-agreement-non-commercial.html
License-File: LICENSE
Requires-Dist: numpy
Requires-Dist: pandas
Requires-Dist: setuptools
Requires-Dist: scikit-learn
Requires-Dist: torch<=2.3.1
Requires-Dist: matplotlib
Requires-Dist: optuna
Dynamic: author
Dynamic: author-email
Dynamic: description
Dynamic: description-content-type
Dynamic: license
Dynamic: requires-dist
Dynamic: summary
